windows_auth/__init__.py
windows_auth/admin.py
windows_auth/apps.py
windows_auth/backends.py
windows_auth/conf.py
windows_auth/decorators.py
windows_auth/ldap.py
windows_auth/middleware.py
windows_auth/models.py
windows_auth/panels.py
windows_auth/predefined_tasks.py
windows_auth/scheduler.py
windows_auth/settings.py
windows_auth/signals.py
windows_auth/utils.py
windows_auth/ldap_metrics/__init__.py
windows_auth/ldap_metrics/admin.py
windows_auth/ldap_metrics/apps.py
windows_auth/ldap_metrics/models.py
windows_auth/ldap_metrics/utils.py
windows_auth/ldap_metrics/migrations/0001_initial.py
windows_auth/ldap_metrics/migrations/__init__.py
windows_auth/management/__init__.py
windows_auth/management/commands/__init__.py
windows_auth/management/commands/createtask.py
windows_auth/management/commands/createwebconfig.py
windows_auth/migrations/0001_initial.py
windows_auth/migrations/0002_auto_20201205_2300.py
windows_auth/migrations/__init__.py
windows_auth/templates/windows_auth/iis_configs/root.config
windows_auth/templates/windows_auth/iis_configs/serve.config
windows_auth/templates/windows_auth/panel/details_base.html
windows_auth/templates/windows_auth/panel/entry_base.html
windows_auth/templates/windows_auth/panel/modify_details.html
windows_auth/templates/windows_auth/panel/modify_entry.html
windows_auth/templates/windows_auth/panel/panel.html
windows_auth/templates/windows_auth/panel/search_details.html
windows_auth/templates/windows_auth/panel/search_entry.html
django_windowsauth-1.4.0.dist-info/LICENSE
django_windowsauth-1.4.0.dist-info/METADATA
django_windowsauth-1.4.0.dist-info/WHEEL
django_windowsauth-1.4.0.dist-info/top_level.txt
django_windowsauth-1.4.0.dist-info/RECORD
